{
  "timestamp": "2026-03-15T10:32:08.444774+00:00",
  "source": "geckoterminal_v2",
  "candidates": [
    {
      "token": {
        "address": "0x627c717c2ded5a3c0427dcabc2d955a49349fc99",
        "symbol": "POKEPULL",
        "name": "POKEPULL"
      },
      "metrics": {
        "liq_usd": 154460.9606,
        "vol_24h_usd": 1063.89355856,
        "txns_24h": 34,
        "price_usd": 0
      },
      "risk": {
        "level": "low",
        "factors": [
          "new_token"
        ]
      },
      "score": 100,
      "age_hours": 0.15025527805555555,
      "detected_at": "2026-03-15T10:32:08.110026+00:00",
      "source": "geckoterminal_v2",
      "badges": [
        "\ud83d\udd25 FRESH",
        "\ud83d\udcb0 WHALE",
        "\u2b50 GEM"
      ]
    }
  ]
}