{
  "meta": {
    "updated_at": "2026-03-06T01:17:43.116Z",
    "source": "cio",
    "chain": "base",
    "count": 3,
    "errors": []
  },
  "signals": [
    {
      "kind": "LURKER_SIGNAL",
      "status": "active",
      "ts_utc": "2026-03-06T01:17:42.765095+00:00",
      "chain": "base",
      "token": {
        "name": "POKEPULL",
        "symbol": "$POKEPULL",
        "address": "0x331db1e809521dbb36c9818537396150f4922d70"
      },
      "scores": {
        "confidence": 100,
        "rarity": "new",
        "risk": "medium"
      },
      "metrics": {
        "price_usd": 0,
        "mcap_usd": 0,
        "liq_usd": 137266.5454,
        "vol_24h_usd": 1691.492733
      },
      "dex": "geckoterminal",
      "pair_address": "0x331db1e809521dbb36c9818537396150f4922d70",
      "scanner": "cio"
    },
    {
      "kind": "LURKER_SIGNAL",
      "status": "active",
      "ts_utc": "2026-03-06T01:17:42.903570+00:00",
      "chain": "base",
      "token": {
        "name": "LUFFY",
        "symbol": "$LUFFY",
        "address": "0xfb5f2d5bbe7fa713d8f8d58646c1d497cab0cdac"
      },
      "scores": {
        "confidence": 100,
        "rarity": "new",
        "risk": "medium"
      },
      "metrics": {
        "price_usd": 0,
        "mcap_usd": 0,
        "liq_usd": 85525.0382,
        "vol_24h_usd": 1297.88132
      },
      "dex": "geckoterminal",
      "pair_address": "0xfb5f2d5bbe7fa713d8f8d58646c1d497cab0cdac",
      "scanner": "cio"
    },
    {
      "kind": "LURKER_SIGNAL",
      "status": "active",
      "ts_utc": "2026-03-06T01:17:43.089047+00:00",
      "chain": "base",
      "token": {
        "name": "Elsa",
        "symbol": "$ELSA",
        "address": "0x35b9561bb3c5609dbaee3b51c503ec1a698f3cfe"
      },
      "scores": {
        "confidence": 100,
        "rarity": "new",
        "risk": "medium"
      },
      "metrics": {
        "price_usd": 0,
        "mcap_usd": 0,
        "liq_usd": 89419.8028,
        "vol_24h_usd": 1171.005471
      },
      "dex": "geckoterminal",
      "pair_address": "0x35b9561bb3c5609dbaee3b51c503ec1a698f3cfe",
      "scanner": "cio"
    }
  ]
}