{
  "meta": {
    "updated_at": "2026-03-05T19:36:43.968Z",
    "source": "cio",
    "chain": "base",
    "count": 3,
    "errors": []
  },
  "signals": [
    {
      "kind": "LURKER_SIGNAL",
      "status": "active",
      "ts_utc": "2026-03-05T19:36:43.644359+00:00",
      "chain": "base",
      "token": {
        "name": "CL",
        "symbol": "$CL",
        "address": "0x5ee277d8b03f2487f209ff6113dd9c66574c962a"
      },
      "scores": {
        "confidence": 100,
        "rarity": "new",
        "risk": "low"
      },
      "metrics": {
        "price_usd": 0,
        "mcap_usd": 0,
        "liq_usd": 22747.3835,
        "vol_24h_usd": 21874.3966861805
      },
      "dex": "geckoterminal",
      "pair_address": "0x5ee277d8b03f2487f209ff6113dd9c66574c962a",
      "scanner": "cio"
    },
    {
      "kind": "LURKER_SIGNAL",
      "status": "active",
      "ts_utc": "2026-03-05T19:36:43.940721+00:00",
      "chain": "base",
      "token": {
        "name": "Mei",
        "symbol": "$MEI",
        "address": "0x205241f60e93ba7370478db9b788a86e832aeba3"
      },
      "scores": {
        "confidence": 100,
        "rarity": "new",
        "risk": "low"
      },
      "metrics": {
        "price_usd": 0,
        "mcap_usd": 0,
        "liq_usd": 12118.5639,
        "vol_24h_usd": 4905.0323748043
      },
      "dex": "geckoterminal",
      "pair_address": "0x205241f60e93ba7370478db9b788a86e832aeba3",
      "scanner": "cio"
    },
    {
      "kind": "LURKER_SIGNAL",
      "status": "active",
      "ts_utc": "2026-03-05T19:36:43.802149+00:00",
      "chain": "base",
      "token": {
        "name": "jatevo",
        "symbol": "$JATEVO",
        "address": "0xaf0e5476d46909210b24377b64059dfb2d9feba3"
      },
      "scores": {
        "confidence": 95,
        "rarity": "new",
        "risk": "low"
      },
      "metrics": {
        "price_usd": 0,
        "mcap_usd": 0,
        "liq_usd": 21986.2317,
        "vol_24h_usd": 5789.1226346436
      },
      "dex": "geckoterminal",
      "pair_address": "0xaf0e5476d46909210b24377b64059dfb2d9feba3",
      "scanner": "cio"
    }
  ]
}