{
  "type": "OPPORTUNITY",
  "token": {
    "address": "0x39b4b879b8521d6a8c3a87cda64b969327b7fba3",
    "symbol": "UNKNOWN",
    "name": "TACHI / WETH",
    "metrics": {
      "liq_usd": 82451.0789,
      "vol_24h_usd": 60195.9566161901,
      "txns_24h": 0,
      "price_usd": 1.05930353735085e-06
    },
    "risk": {
      "level": "medium",
      "factors": [
        "moderate_liquidity",
        "low_activity"
      ]
    },
    "first_seen": "2026-03-19T11:55:37.858404+00:00",
    "status": "NEW"
  },
  "timestamp": "2026-03-19T12:04:45.760485+00:00"
}